bios_extractor/__init__.py
bios_extractor/main.py
bios_extractor/conf/__init__.py
bios_extractor/lib/__init__.py
bios_extractor-0.1.0.dist-info/METADATA
bios_extractor-0.1.0.dist-info/WHEEL
bios_extractor-0.1.0.dist-info/entry_points.txt
bios_extractor-0.1.0.dist-info/top_level.txt
bios_extractor-0.1.0.dist-info/RECORD
