Metadata-Version: 2.4
Name: bios_extractor
Version: 0.1.0
Summary: BIOS Update Extraktor für ISO und EXE Dateien
Home-page: https://github.com/alientools-org/bios_extractor
Author: hexzhen3x7
Author-email: hexzhen3x7 <hexzhen3x7@blackzspace.de>
License: MIT
Keywords: bios,extractor,iso,exe,firmware
Classifier: Programming Language :: Python :: 3
Classifier: Operating System :: POSIX :: Linux
Classifier: License :: OSI Approved :: MIT License
Classifier: Topic :: Utilities
Requires-Python: >=3.7
Dynamic: author
Dynamic: home-page
Dynamic: requires-python
